massif_to_csv.py
massif_to_csv-0.1.0.data/scripts/massif-to-csv
massif_to_csv-0.1.0.dist-info/LICENSE
massif_to_csv-0.1.0.dist-info/METADATA
massif_to_csv-0.1.0.dist-info/WHEEL
massif_to_csv-0.1.0.dist-info/top_level.txt
massif_to_csv-0.1.0.dist-info/RECORD
